flexx/__init__.py
flexx/__main__.py
flexx/_config.py
flexx/flx.py
flexx/flx_flask.py
flexx/app/__init__.py
flexx/app/_app.py
flexx/app/_asset.py
flexx/app/_assetstore.py
flexx/app/_clientcore.py
flexx/app/_component2.py
flexx/app/_flaskhelpers.py
flexx/app/_flaskserver.py
flexx/app/_funcs.py
flexx/app/_modules.py
flexx/app/_server.py
flexx/app/_session.py
flexx/app/_tornadoserver.py
flexx/app/bsdf_lite.py
flexx/app/live_tester.py
flexx/event/__init__.py
flexx/event/_action.py
flexx/event/_attribute.py
flexx/event/_component.py
flexx/event/_dict.py
flexx/event/_emitter.py
flexx/event/_js.py
flexx/event/_loop.py
flexx/event/_property.py
flexx/event/_reaction.py
flexx/event/both_tester.py
flexx/resources/README.md
flexx/resources/bb64.js
flexx/resources/bsdf.js
flexx/resources/flexx.ico
flexx/resources/flexx.png
flexx/resources/iconmaker.py
flexx/resources/phosphor-all.94d59b003849f.css
flexx/resources/phosphor-all.94d59b003849f.js
flexx/ui/__init__.py
flexx/ui/_widget.py
flexx/ui/layouts/__init__.py
flexx/ui/layouts/_form.py
flexx/ui/layouts/_grid.py
flexx/ui/layouts/_hv.py
flexx/ui/layouts/_layout.py
flexx/ui/layouts/_pinboard.py
flexx/ui/layouts/_stack.py
flexx/ui/layouts/_tabs.py
flexx/ui/pywidgets/__init__.py
flexx/ui/pywidgets/_filebrowser.py
flexx/ui/widgets/__init__.py
flexx/ui/widgets/_bokeh.py
flexx/ui/widgets/_button.py
flexx/ui/widgets/_canvas.py
flexx/ui/widgets/_color.py
flexx/ui/widgets/_dropdown.py
flexx/ui/widgets/_group.py
flexx/ui/widgets/_iframe.py
flexx/ui/widgets/_label.py
flexx/ui/widgets/_lineedit.py
flexx/ui/widgets/_markdown.py
flexx/ui/widgets/_media.py
flexx/ui/widgets/_plotly.py
flexx/ui/widgets/_plotwidget.py
flexx/ui/widgets/_progressbar.py
flexx/ui/widgets/_slider.py
flexx/ui/widgets/_tree.py
flexx/util/__init__.py
flexx/util/config.py
flexx/util/freeze.py
flexx/util/getresource.py
flexx/util/logging.py
flexx/util/minify.py
flexx/util/screenshot.py
flexx/util/testing.py
flexxamples/__init__.py
flexxamples/demos/__init__.py
flexx-0.8.4.dist-info/LICENSE
flexx-0.8.4.dist-info/METADATA
flexx-0.8.4.dist-info/WHEEL
flexx-0.8.4.dist-info/entry_points.txt
flexx-0.8.4.dist-info/top_level.txt
flexx-0.8.4.dist-info/RECORD
