Metadata-Version: 2.1
Name: flexx
Version: 0.8.4
Summary: Write desktop and web apps in pure Python.
Home-page: https://flexx.readthedocs.io
Author: Flexx contributors
Author-email: almar.klein@gmail.com
License: (new) BSD
Download-URL: https://pypi.python.org/pypi/flexx
Project-URL: Documentation, https://flexx.readthedocs.io
Keywords: ui design,GUI,web,runtime,pyscript,events,properties
Platform: any
Classifier: Development Status :: 4 - Beta
Classifier: Intended Audience :: Science/Research
Classifier: Intended Audience :: Developers
Classifier: Topic :: Software Development :: User Interfaces
Classifier: Topic :: Internet :: WWW/HTTP
Classifier: License :: OSI Approved :: BSD License
Classifier: Operating System :: MacOS :: MacOS X
Classifier: Operating System :: Microsoft :: Windows
Classifier: Operating System :: POSIX
Classifier: Programming Language :: JavaScript
Classifier: Programming Language :: Python
Classifier: Programming Language :: Python :: 3.5
Classifier: Programming Language :: Python :: 3.6
Classifier: Programming Language :: Python :: 3.7
Classifier: Programming Language :: Python :: 3.8
Classifier: Programming Language :: Python :: 3.9
Provides: flexx
Requires-Python: >=3.5
License-File: LICENSE
